{
  "coord": {
    "lon": -1.0913,
    "lat": 50.799
  },
  "weather": [
    {
      "id": 800,
      "main": "Clear",
      "description": "clear sky",
      "icon": "01d"
    }
  ],
  "base": "stations",
  "main": {
    "temp": 30.11,
    "feels_like": 30.32,
    "temp_min": 28.43,
    "temp_max": 30.66,
    "pressure": 1021,
    "humidity": 44,
    "sea_level": 1021,
    "grnd_level": 1018
  },
  "visibility": 10000,
  "wind": {
    "speed": 9.82,
    "deg": 65,
    "gust": 12.32
  },
  "clouds": {
    "all": 9
  },
  "dt": 1783867694,
  "sys": {
    "type": 2,
    "id": 2041190,
    "country": "GB",
    "sunrise": 1783829072,
    "sunset": 1783887298
  },
  "timezone": 3600,
  "id": 2639996,
  "name": "Portsmouth",
  "cod": 200,
  "_last_updated_utc": "2026-07-12T14:48:14.833Z"
}