{
  "coord": {
    "lon": -1.0913,
    "lat": 50.799
  },
  "weather": [
    {
      "id": 804,
      "main": "Clouds",
      "description": "overcast clouds",
      "icon": "04d"
    }
  ],
  "base": "stations",
  "main": {
    "temp": 20.03,
    "feels_like": 19.58,
    "temp_min": 20.03,
    "temp_max": 20.66,
    "pressure": 1015,
    "humidity": 57,
    "sea_level": 1015,
    "grnd_level": 1012
  },
  "visibility": 10000,
  "wind": {
    "speed": 5.53,
    "deg": 96,
    "gust": 7.84
  },
  "clouds": {
    "all": 89
  },
  "dt": 1778337589,
  "sys": {
    "type": 1,
    "id": 1402,
    "country": "GB",
    "sunrise": 1778300689,
    "sunset": 1778355411
  },
  "timezone": 3600,
  "id": 2639996,
  "name": "Portsmouth",
  "cod": 200,
  "_last_updated_utc": "2026-05-09T14:42:48.716Z"
}