{
  "coord": {
    "lon": -1.0913,
    "lat": 50.799
  },
  "weather": [
    {
      "id": 800,
      "main": "Clear",
      "description": "clear sky",
      "icon": "01d"
    }
  ],
  "base": "stations",
  "main": {
    "temp": 27.44,
    "feels_like": 27.64,
    "temp_min": 26.23,
    "temp_max": 28.99,
    "pressure": 1016,
    "humidity": 47,
    "sea_level": 1016,
    "grnd_level": 1014
  },
  "visibility": 10000,
  "wind": {
    "speed": 2.05,
    "deg": 181,
    "gust": 2.96
  },
  "clouds": {
    "all": 8
  },
  "dt": 1784286987,
  "sys": {
    "type": 2,
    "id": 2041190,
    "country": "GB",
    "sunrise": 1784261411,
    "sunset": 1784319024
  },
  "timezone": 3600,
  "id": 2639996,
  "name": "Portsmouth",
  "cod": 200,
  "_last_updated_utc": "2026-07-17T11:16:27.724Z"
}