{
  "coord": {
    "lon": -1.0913,
    "lat": 50.799
  },
  "weather": [
    {
      "id": 801,
      "main": "Clouds",
      "description": "few clouds",
      "icon": "02d"
    }
  ],
  "base": "stations",
  "main": {
    "temp": 20.12,
    "feels_like": 20.2,
    "temp_min": 20.12,
    "temp_max": 20.12,
    "pressure": 1023,
    "humidity": 77,
    "sea_level": 1023,
    "grnd_level": 1020
  },
  "visibility": 10000,
  "wind": {
    "speed": 3.76,
    "deg": 121,
    "gust": 3.8
  },
  "clouds": {
    "all": 16
  },
  "dt": 1775645281,
  "sys": {
    "country": "GB",
    "sunrise": 1775625909,
    "sunset": 1775674017
  },
  "timezone": 3600,
  "id": 2639996,
  "name": "Portsmouth",
  "cod": 200,
  "_last_updated_utc": "2026-04-08T10:50:56.273Z"
}