{
  "coord": {
    "lon": -1.0913,
    "lat": 50.799
  },
  "weather": [
    {
      "id": 804,
      "main": "Clouds",
      "description": "overcast clouds",
      "icon": "04d"
    }
  ],
  "base": "stations",
  "main": {
    "temp": 22.76,
    "feels_like": 23.1,
    "temp_min": 20,
    "temp_max": 22.76,
    "pressure": 1024,
    "humidity": 77,
    "sea_level": 1024,
    "grnd_level": 1021
  },
  "visibility": 10000,
  "wind": {
    "speed": 0.45,
    "deg": 252,
    "gust": 1.34
  },
  "clouds": {
    "all": 96
  },
  "dt": 1782029959,
  "sys": {
    "type": 2,
    "id": 2008636,
    "country": "GB",
    "sunrise": 1782013848,
    "sunset": 1782073282
  },
  "timezone": 3600,
  "id": 2639996,
  "name": "Portsmouth",
  "cod": 200,
  "_last_updated_utc": "2026-06-21T08:21:46.665Z"
}