{
  "coord": {
    "lon": -1.0913,
    "lat": 50.799
  },
  "weather": [
    {
      "id": 804,
      "main": "Clouds",
      "description": "overcast clouds",
      "icon": "04n"
    }
  ],
  "base": "stations",
  "main": {
    "temp": 4.78,
    "feels_like": 2.49,
    "temp_min": 3.73,
    "temp_max": 5.51,
    "pressure": 1031,
    "humidity": 87,
    "sea_level": 1031,
    "grnd_level": 1028
  },
  "visibility": 10000,
  "wind": {
    "speed": 2.68,
    "deg": 44,
    "gust": 5.81
  },
  "clouds": {
    "all": 100
  },
  "dt": 1767075599,
  "sys": {
    "type": 2,
    "id": 2008636,
    "country": "GB",
    "sunrise": 1767081997,
    "sunset": 1767110814
  },
  "timezone": 0,
  "id": 2639996,
  "name": "Portsmouth",
  "cod": 200,
  "_last_updated_utc": "2025-12-30T06:23:08.953Z"
}