{
  "coord": {
    "lon": -1.0913,
    "lat": 50.799
  },
  "weather": [
    {
      "id": 804,
      "main": "Clouds",
      "description": "overcast clouds",
      "icon": "04n"
    }
  ],
  "base": "stations",
  "main": {
    "temp": 4.11,
    "feels_like": -1.59,
    "temp_min": 3.43,
    "temp_max": 4.95,
    "pressure": 1013,
    "humidity": 85,
    "sea_level": 1013,
    "grnd_level": 1009
  },
  "visibility": 10000,
  "wind": {
    "speed": 10.02,
    "deg": 182,
    "gust": 12.24
  },
  "clouds": {
    "all": 100
  },
  "dt": 1771128835,
  "sys": {
    "type": 2,
    "id": 2041190,
    "country": "GB",
    "sunrise": 1771139832,
    "sunset": 1771176003
  },
  "timezone": 0,
  "id": 2639996,
  "name": "Portsmouth",
  "cod": 200,
  "_last_updated_utc": "2026-02-15T04:14:54.145Z"
}