{
  "coord": {
    "lon": -1.0913,
    "lat": 50.799
  },
  "weather": [
    {
      "id": 800,
      "main": "Clear",
      "description": "clear sky",
      "icon": "01d"
    }
  ],
  "base": "stations",
  "main": {
    "temp": 25.63,
    "feels_like": 25.63,
    "temp_min": 25.54,
    "temp_max": 26.23,
    "pressure": 1017,
    "humidity": 53,
    "sea_level": 1017,
    "grnd_level": 1014
  },
  "visibility": 10000,
  "wind": {
    "speed": 2.24,
    "deg": 200,
    "gust": 4.02
  },
  "clouds": {
    "all": 8
  },
  "dt": 1784281797,
  "sys": {
    "type": 2,
    "id": 2008636,
    "country": "GB",
    "sunrise": 1784261411,
    "sunset": 1784319024
  },
  "timezone": 3600,
  "id": 2639996,
  "name": "Portsmouth",
  "cod": 200,
  "_last_updated_utc": "2026-07-17T09:49:57.548Z"
}