{
  "coord": {
    "lon": -1.0913,
    "lat": 50.799
  },
  "weather": [
    {
      "id": 804,
      "main": "Clouds",
      "description": "overcast clouds",
      "icon": "04d"
    }
  ],
  "base": "stations",
  "main": {
    "temp": 15.97,
    "feels_like": 15.71,
    "temp_min": 15.55,
    "temp_max": 16.21,
    "pressure": 1020,
    "humidity": 80,
    "sea_level": 1020,
    "grnd_level": 1017
  },
  "visibility": 10000,
  "wind": {
    "speed": 2.68,
    "deg": 224,
    "gust": 5.36
  },
  "clouds": {
    "all": 100
  },
  "dt": 1780852018,
  "sys": {
    "type": 2,
    "id": 2008636,
    "country": "GB",
    "sunrise": 1780804374,
    "sunset": 1780863226
  },
  "timezone": 3600,
  "id": 2639996,
  "name": "Portsmouth",
  "cod": 200,
  "_last_updated_utc": "2026-06-07T17:06:58.373Z"
}