{
  "coord": {
    "lon": -1.0913,
    "lat": 50.799
  },
  "weather": [
    {
      "id": 804,
      "main": "Clouds",
      "description": "overcast clouds",
      "icon": "04n"
    }
  ],
  "base": "stations",
  "main": {
    "temp": 6.59,
    "feels_like": 4.64,
    "temp_min": 5.66,
    "temp_max": 7.21,
    "pressure": 990,
    "humidity": 94,
    "sea_level": 990,
    "grnd_level": 986
  },
  "visibility": 10000,
  "wind": {
    "speed": 2.68,
    "deg": 70,
    "gust": 5.81
  },
  "clouds": {
    "all": 100
  },
  "dt": 1770091700,
  "sys": {
    "type": 2,
    "id": 2008636,
    "country": "GB",
    "sunrise": 1770104262,
    "sunset": 1770137915
  },
  "timezone": 0,
  "id": 2639996,
  "name": "Portsmouth",
  "cod": 200,
  "_last_updated_utc": "2026-02-03T04:08:20.661Z"
}