{
  "coord": {
    "lon": -1.0913,
    "lat": 50.799
  },
  "weather": [
    {
      "id": 802,
      "main": "Clouds",
      "description": "scattered clouds",
      "icon": "03n"
    }
  ],
  "base": "stations",
  "main": {
    "temp": 12.85,
    "feels_like": 12.31,
    "temp_min": 11.51,
    "temp_max": 13.84,
    "pressure": 1018,
    "humidity": 81,
    "sea_level": 1018,
    "grnd_level": 1015
  },
  "visibility": 10000,
  "wind": {
    "speed": 4.02,
    "deg": 285,
    "gust": 6.71
  },
  "clouds": {
    "all": 25
  },
  "dt": 1780800486,
  "sys": {
    "type": 2,
    "id": 2008636,
    "country": "GB",
    "sunrise": 1780804374,
    "sunset": 1780863226
  },
  "timezone": 3600,
  "id": 2639996,
  "name": "Portsmouth",
  "cod": 200,
  "_last_updated_utc": "2026-06-07T02:48:06.732Z"
}